Workbook

Sheet Supuestos
A1: Variable | B1: Conservador | C1: Base | D1: Expansivo | E1: Unidad | F1: Origen / nota
A2: Proyectos de producción / mes | B2: 2 | C2: 4 | D2: 7 | E2: proyectos | F2: Supuesto editable; no es dato histórico
A3: Ticket medio de producción | B3: 500 | C3: 750 | D3: 1000 | E3: EUR | F3: Supuesto editable
A4: Beats no exclusivos / mes | B4: 3 | C4: 8 | D4: 15 | E4: ventas | F4: Supuesto editable
A5: Precio medio beat no exclusivo | B5: 60 | C5: 75 | D5: 90 | E5: EUR | F5: Supuesto editable
A6: Beats exclusivos / mes | B6: 0 | C6: 1 | D6: 2 | E6: ventas | F6: Supuesto editable
A7: Precio medio beat exclusivo | B7: 0 | C7: 450 | D7: 700 | E7: EUR | F7: Supuesto editable
A8: Retainers / mes | B8: 0 | C8: 1 | D8: 3 | E8: clientes | F8: Supuesto editable
A9: Precio medio retainer | B9: 0 | C9: 600 | D9: 900 | E9: EUR | F9: Supuesto editable
A10: Coste variable / proyecto | B10: 120 | C10: 150 | D10: 220 | E10: EUR | F10: Supuesto editable
A11: Coste variable / venta de beat | B11: 5 | C11: 7 | D11: 10 | E11: EUR | F11: Supuesto editable
A12: Coste fijo mensual | B12: 250 | C12: 450 | D12: 850 | E12: EUR | F12: Supuesto editable
A13: Marketing y adquisición mensual | B13: 50 | C13: 150 | D13: 400 | E13: EUR | F13: Supuesto editable
... A17: Clientes perdidos / mes | B17: 1 | C17: 1 | D17: 1 | E17: clientes | F17: Supuesto editable

Sheet Escenarios
A1: Métrica | B1: Conservador | C1: Base | D1: Expansivo | E1: Interpretación
A2: Ingresos producción / mes | B2: =Supuestos!B2*Supuestos!B3 | C2: =Supuestos!C2*Supuestos!C3 | D2: =Supuestos!D2*Supuestos!D3 | E2: Volumen por ticket
A3: Ingresos beats no exclusivos / mes | B3: =Supuestos!B4*Supuestos!B5 | C3: =Supuestos!C4*Supuestos!C5 | D3: =Supuestos!D4*Supuestos!D5 | E3: Catálogo recurrente
A4: Ingresos beats exclusivos / mes | B4: =Supuestos!B6*Supuestos!B7 | C4: =Supuestos!C6*Supuestos!C7 | D4: =Supuestos!D6*Supuestos!D7 | E4: Escasez y licencia
A5: Ingresos retainers / mes | B5: =Supuestos!B8*Supuestos!B9 | C5: =Supuestos!C8*Supuestos!C9 | D5: =Supuestos!D8*Supuestos!D9 | E5: Previsibilidad
A6: Ingresos totales / mes | B6: =SUM(B2:B5) | C6: =SUM(C2:C5) | D6: =SUM(D2:D5) | E6: No equivale a caja cobrada
A7: Costes variables / mes | B7: =Supuestos!B2*Supuestos!B10+Supuestos!B4*Supuestos!B11+Supuestos!B6*Supuestos!B11 | C7: =Supuestos!C2*Supuestos!C10+Supuestos!C4*Supuestos!C11+Supuestos!C6*Supuestos!C11 | D7: =Supuestos!D2*Supuestos!D10+Supuestos!D4*Supuestos!D11+Supuestos!D6*Supuestos!D11 | E7: Antes de costes fijos
A8: Margen de contribución / mes | B8: =B6-B7 | C8: =C6-C7 | D8: =D6-D7 | E8: Ingresos menos variables
A9: Costes fijos + marketing / mes | B9: =Supuestos!B12+Supuestos!B13 | C9: =Supuestos!C12+Supuestos!C13 | D9: =Supuestos!D12+Supuestos!D13 | E9: Gasto operativo
A10: Resultado operativo aproximado / mes | B10: =B8-B9 | C10: =C8-C9 | D10: =D8-D9 | E10: No es beneficio fiscal
A11: Punto de equilibrio de ingresos | B11: =B9/(1-B7/B6) | C11: =C9/(1-C7/C6) | D11: =D9/(1-D7/D6) | E11: Ingresos aproximados
A12: Runway en meses si resultado negativo | B12: =IF(B10<0,Supuestos!B14/MAX(1,-B10),NA()) | C12: =IF(C10<0,Supuestos!C14/MAX(1,-C10),NA()) | D12: =IF(D10<0,Supuestos!D14/MAX(1,-D10),NA()) | E12: Caja / pérdida mensual

Sheet Caja 12 meses
A1: Mes | B1: Caja conservadora | C1: Caja base | D1: Caja expansiva | E1: Clientes activos base
A2: 1 | B2: =Supuestos!B14+Escenarios!B10 | C2: =Supuestos!C14+Escenarios!C10 | D2: =Supuestos!D14+Escenarios!D10 | E2: =MAX(0,Supuestos!C15+Supuestos!C16-Supuestos!C17)
A3: 2 | B3: =B2+Escenarios!B10 | C3: =C2+Escenarios!C10 | D3: =D2+Escenarios!D10 | E3: =MAX(0,E2+Supuestos!C16-Supuestos!C17)
A4: 3 | B4: =B3+Escenarios!B10 | C4: =C3+Escenarios!C10 | D4: =D3+Escenarios!D10 | E4: =MAX(0,E3+Supuestos!C16-Supuestos!C17)
A5: 4 | B5: =B4+Escenarios!B10 | C5: =C4+Escenarios!C10 | D5: =D4+Escenarios!D10 | E5: =MAX(0,E4+Supuestos!C16-Supuestos!C17)
A6: 5 | B6: =B5+Escenarios!B10 | C6: =C5+Escenarios!C10 | D6: =D5+Escenarios!D10 | E6: =MAX(0,E5+Supuestos!C16-Supuestos!C17)
A7: 6 | B7: =B6+Escenarios!B10 | C7: =C6+Escenarios!C10 | D7: =D6+Escenarios!D10 | E7: =MAX(0,E6+Supuestos!C16-Supuestos!C17)
A8: 7 | B8: =B7+Escenarios!B10 | C8: =C7+Escenarios!C10 | D8: =D7+Escenarios!D10 | E8: =MAX(0,E7+Supuestos!C16-Supuestos!C17)
A9: 8 | B9: =B8+Escenarios!B10 | C9: =C8+Escenarios!C10 | D9: =D8+Escenarios!D10 | E9: =MAX(0,E8+Supuestos!C16-Supuestos!C17)
A10: 9 | B10: =B9+Escenarios!B10 | C10: =C9+Escenarios!C10 | D10: =D9+Escenarios!D10 | E10: =MAX(0,E9+Supuestos!C16-Supuestos!C17)
A11: 10 | B11: =B10+Escenarios!B10 | C11: =C10+Escenarios!C10 | D11: =D10+Escenarios!D10 | E11: =MAX(0,E10+Supuestos!C16-Supuestos!C17)
A12: 11 | B12: =B11+Escenarios!B10 | C12: =C11+Escenarios!C10 | D12: =D11+Escenarios!D10 | E12: =MAX(0,E11+Supuestos!C16-Supuestos!C17)
A13: 12 | B13: =B12+Escenarios!B10 | C13: =C12+Escenarios!C10 | D13: =D12+Escenarios!D10 | E13: =MAX(0,E12+Supuestos!C16-Supuestos!C17)

Sheet Riesgos y métricas
A1: Riesgo / métrica | B1: Umbral de alerta | C1: Acción
A2: Concentración del mayor cliente | B2: > 35% de ingresos | C2: Diversificar antes de aumentar costes fijos
A3: Caja proyectada | B3: < 3 meses de costes fijos | C3: Reducir gasto y priorizar cobros
A4: Margen de contribución | B4: < 50% | C4: Revisar ticket, alcance y costes
A5: Revisiones extra | B5: > 20% de proyectos | C5: Reforzar contrato y límite server-side
A6: Pagos atrasados | B6: > 15% de facturas | C6: Cobro anticipado o hitos
A7: Dependencia de un canal | B7: > 60% de leads | C7: Abrir canal directo y catálogo propio
